whale_googleanalytics/.DS_Store
whale_googleanalytics/__init__.py
whale_googleanalytics/main.py
whale_googleanalytics/server/app.py
whale_googleanalytics/server/enum_list.py
whale_googleanalytics/server/gcp_functions.py
whale_googleanalytics/server/helpers/plotly.py
whale_googleanalytics/server/models/model_gcp.py
whale_googleanalytics/server/routes/routes_gcp.py
whale_googleanalytics/server/test_api.py
whale_googleanalytics-1.26.dist-info/entry_points.txt
whale_googleanalytics-1.26.dist-info/WHEEL
whale_googleanalytics-1.26.dist-info/METADATA
whale_googleanalytics-1.26.dist-info/RECORD
